qass/tools/networking/__init__.py
qass/tools/networking/analyzer_socket.py
qass/tools/networking/python_server_client.py
qass/tools/networking/remote_request_operator.py
qass/tools/networking/tests/test_analyzer_socket.py
qass_tools_networking-3.7.dist-info/licenses/COPYING
qass_tools_networking-3.7.dist-info/licenses/COPYING.LESSER
qass_tools_networking-3.7.dist-info/METADATA
qass_tools_networking-3.7.dist-info/WHEEL
qass_tools_networking-3.7.dist-info/top_level.txt
qass_tools_networking-3.7.dist-info/RECORD
