Metadata-Version: 2.4
Name: qass-tools-networking
Version: 3.7
Summary: Networking package for qass_tools
Author-email: Oliver Kowollik <okowollik@qass.net>
Project-URL: Homepage, https://qass.github.io/
Classifier: Programming Language :: Python :: 3
Classifier: License :: OSI Approved :: GNU Lesser General Public License v3 (LGPLv3)
Classifier: Operating System :: OS Independent
Requires-Python: >=3.6
License-File: COPYING
License-File: COPYING.LESSER
Requires-Dist: retry
Requires-Dist: numpy>=1.19.5
Requires-Dist: packaging
Provides-Extra: developers
Requires-Dist: pytest; extra == "developers"
Requires-Dist: enum-tools; extra == "developers"
Requires-Dist: Sphinx; extra == "developers"
Requires-Dist: sphinx_toolbox; extra == "developers"
Requires-Dist: sphinx_design; extra == "developers"
Requires-Dist: sphinx-rtd-theme; extra == "developers"
Provides-Extra: gui
Requires-Dist: PySide2; extra == "gui"
Dynamic: license-file
